example_stainless/__init__.py
example_stainless/_base_client.py
example_stainless/_client.py
example_stainless/_compat.py
example_stainless/_constants.py
example_stainless/_exceptions.py
example_stainless/_files.py
example_stainless/_models.py
example_stainless/_qs.py
example_stainless/_resource.py
example_stainless/_response.py
example_stainless/_streaming.py
example_stainless/_types.py
example_stainless/_version.py
example_stainless/py.typed
example_stainless/_utils/__init__.py
example_stainless/_utils/_logs.py
example_stainless/_utils/_proxy.py
example_stainless/_utils/_reflection.py
example_stainless/_utils/_streams.py
example_stainless/_utils/_sync.py
example_stainless/_utils/_transform.py
example_stainless/_utils/_typing.py
example_stainless/_utils/_utils.py
example_stainless/lib/.keep
example_stainless/resources/__init__.py
example_stainless/resources/pets.py
example_stainless/resources/user.py
example_stainless/resources/store/__init__.py
example_stainless/resources/store/order.py
example_stainless/resources/store/store.py
example_stainless/types/__init__.py
example_stainless/types/api_response.py
example_stainless/types/category.py
example_stainless/types/category_param.py
example_stainless/types/pet.py
example_stainless/types/pet_create_params.py
example_stainless/types/pet_find_by_status_params.py
example_stainless/types/pet_find_by_status_response.py
example_stainless/types/pet_find_by_tags_params.py
example_stainless/types/pet_find_by_tags_response.py
example_stainless/types/pet_update_by_id_params.py
example_stainless/types/pet_update_params.py
example_stainless/types/pet_upload_image_params.py
example_stainless/types/store_create_order_params.py
example_stainless/types/store_inventory_response.py
example_stainless/types/user.py
example_stainless/types/user_create_params.py
example_stainless/types/user_create_with_list_params.py
example_stainless/types/user_login_params.py
example_stainless/types/user_login_response.py
fuando_example_stainless-0.1.0a1.dist-info/METADATA
fuando_example_stainless-0.1.0a1.dist-info/WHEEL
fuando_example_stainless-0.1.0a1.dist-info/licenses/LICENSE
fuando_example_stainless-0.1.0a1.dist-info/RECORD
